asyncio_loop_local/__init__.py
asyncio_loop_local/_atexit.py
asyncio_loop_local/_enter.py
asyncio_loop_local/_enter_once.py
asyncio_loop_local/_singleton.py
asyncio_loop_local/_sticky_acm.py
asyncio_loop_local/_sticky_singleton_acm.py
asyncio_loop_local/_storage.py
asyncio_loop_local/py.typed
asyncio_loop_local-0.0.4.dist-info/LICENSE
asyncio_loop_local-0.0.4.dist-info/METADATA
asyncio_loop_local-0.0.4.dist-info/WHEEL
asyncio_loop_local-0.0.4.dist-info/top_level.txt
asyncio_loop_local-0.0.4.dist-info/RECORD
