Metadata-Version: 2.1
Name: asyncio-loop-local
Version: 0.0.4
Summary: asyncio-loop-local storage, singletons and deferred __aexit__'s. Init that pool once and reuse it!
Author-email: Alexander Sosedkin <monk@unboiled.info>
License: GNU GENERAL PUBLIC LICENSE
Project-URL: homepage, https://github.com/t184256/asyncio-loop-local
Classifier: Programming Language :: Python :: 3
Classifier: License :: OSI Approved :: GNU General Public License v3 (GPLv3)
Requires-Python: >=3.11
License-File: LICENSE
Provides-Extra: test
Requires-Dist: pytest ; extra == 'test'
Requires-Dist: pytest-asyncio ; extra == 'test'
Requires-Dist: coverage ; extra == 'test'
Requires-Dist: pytest-cov ; extra == 'test'
Requires-Dist: mypy ; extra == 'test'
Requires-Dist: pytest-mypy ; extra == 'test'
Requires-Dist: ruff ; extra == 'test'
